JavaShejimoshi23ZhongShejimoshiQuanmianJiexiCYuyanZhongwenwang/README.md
JavaShejimoshi23ZhongShejimoshiQuanmianJiexiCYuyanZhongwenwang/__init__.py
JavaShejimoshi23ZhongShejimoshiQuanmianJiexiCYuyanZhongwenwang/__main__.py
JavaShejimoshi23ZhongShejimoshiQuanmianJiexiCYuyanZhongwenwang/file.epub
JavaShejimoshi23ZhongShejimoshiQuanmianJiexiCYuyanZhongwenwang/index.html
JavaShejimoshi23ZhongShejimoshiQuanmianJiexiCYuyanZhongwenwang/css/__init__.py
JavaShejimoshi23ZhongShejimoshiQuanmianJiexiCYuyanZhongwenwang/css/annotations.css
JavaShejimoshi23ZhongShejimoshiQuanmianJiexiCYuyanZhongwenwang/css/main.css
JavaShejimoshi23ZhongShejimoshiQuanmianJiexiCYuyanZhongwenwang/css/normalize.css
JavaShejimoshi23ZhongShejimoshiQuanmianJiexiCYuyanZhongwenwang/css/popup.css
JavaShejimoshi23ZhongShejimoshiQuanmianJiexiCYuyanZhongwenwang/font/__init__.py
JavaShejimoshi23ZhongShejimoshiQuanmianJiexiCYuyanZhongwenwang/font/fontello.eot
JavaShejimoshi23ZhongShejimoshiQuanmianJiexiCYuyanZhongwenwang/font/fontello.svg
JavaShejimoshi23ZhongShejimoshiQuanmianJiexiCYuyanZhongwenwang/font/fontello.ttf
JavaShejimoshi23ZhongShejimoshiQuanmianJiexiCYuyanZhongwenwang/font/fontello.woff
JavaShejimoshi23ZhongShejimoshiQuanmianJiexiCYuyanZhongwenwang/img/__init__.py
JavaShejimoshi23ZhongShejimoshiQuanmianJiexiCYuyanZhongwenwang/img/annotator-glyph-sprite.png
JavaShejimoshi23ZhongShejimoshiQuanmianJiexiCYuyanZhongwenwang/img/annotator-icon-sprite.png
JavaShejimoshi23ZhongShejimoshiQuanmianJiexiCYuyanZhongwenwang/img/apple-touch-icon.png
JavaShejimoshi23ZhongShejimoshiQuanmianJiexiCYuyanZhongwenwang/img/cancelfullscreen.png
JavaShejimoshi23ZhongShejimoshiQuanmianJiexiCYuyanZhongwenwang/img/close.png
JavaShejimoshi23ZhongShejimoshiQuanmianJiexiCYuyanZhongwenwang/img/fullscreen.png
JavaShejimoshi23ZhongShejimoshiQuanmianJiexiCYuyanZhongwenwang/img/loader.gif
JavaShejimoshi23ZhongShejimoshiQuanmianJiexiCYuyanZhongwenwang/img/menu-icon.png
java_shejimoshi_23_zhong_shejimoshi_quanmian_jiexi_c_yuyan_zhongwenwang-2024.3.4.0.dist-info/METADATA
java_shejimoshi_23_zhong_shejimoshi_quanmian_jiexi_c_yuyan_zhongwenwang-2024.3.4.0.dist-info/WHEEL
java_shejimoshi_23_zhong_shejimoshi_quanmian_jiexi_c_yuyan_zhongwenwang-2024.3.4.0.dist-info/entry_points.txt
java_shejimoshi_23_zhong_shejimoshi_quanmian_jiexi_c_yuyan_zhongwenwang-2024.3.4.0.dist-info/top_level.txt
java_shejimoshi_23_zhong_shejimoshi_quanmian_jiexi_c_yuyan_zhongwenwang-2024.3.4.0.dist-info/RECORD
